streamlit_drawable_canvas/__init__.py
streamlit_drawable_canvas/frontend/build/asset-manifest.json
streamlit_drawable_canvas/frontend/build/index.html
streamlit_drawable_canvas/frontend/build/static/css/main.8802268d.chunk.css
streamlit_drawable_canvas/frontend/build/static/css/main.8802268d.chunk.css.map
streamlit_drawable_canvas/frontend/build/static/js/2.526b384d.chunk.js
streamlit_drawable_canvas/frontend/build/static/js/2.526b384d.chunk.js.LICENSE.txt
streamlit_drawable_canvas/frontend/build/static/js/2.526b384d.chunk.js.map
streamlit_drawable_canvas/frontend/build/static/js/main.553854dd.chunk.js
streamlit_drawable_canvas/frontend/build/static/js/main.553854dd.chunk.js.map
streamlit_drawable_canvas/frontend/build/static/js/runtime-main.3def19be.js
streamlit_drawable_canvas/frontend/build/static/js/runtime-main.3def19be.js.map
landingai_streamlit_drawable_canvas-0.9.8.dist-info/LICENSE
landingai_streamlit_drawable_canvas-0.9.8.dist-info/METADATA
landingai_streamlit_drawable_canvas-0.9.8.dist-info/WHEEL
landingai_streamlit_drawable_canvas-0.9.8.dist-info/top_level.txt
landingai_streamlit_drawable_canvas-0.9.8.dist-info/RECORD
