Metadata-Version: 2.1
Name: landingai-streamlit-drawable-canvas
Version: 0.9.8
Summary: A Streamlit custom component for a free drawing canvas using Fabric.js.
Home-page: https://github.com/AsiaCao/streamlit-drawable-canvas
Author: Fanilo ANDRIANASOLO
Author-email: contact@andfanilo.com
License: UNKNOWN
Platform: UNKNOWN
Requires-Python: >=3.6
License-File: LICENSE
Requires-Dist: Pillow
Requires-Dist: numpy
Requires-Dist: streamlit (>=0.63)
